forecast_clarify/__init__.py
forecast_clarify/clarify_persistence_package.py
forecast_clarify/config.py
forecast_clarify/main.py
forecast_clarify/data/__init__.py
forecast_clarify/data/external/__init__.py
forecast_clarify/data/external/barentswatch_sites.json
forecast_clarify/data/processed/__init__.py
forecast_clarify/data/processed/temperature_insitu_3m_norkyst800_barentswatch_closest_20060101-20220920_persistence.nc
forecast_clarify/data/processed/temperature_insitu_3m_norkyst800_barentswatch_closest_20060101-20220920_persistence_seasonal_cycle_61D-wndw_3harm.nc
forecast_clarify/data/processed/temperature_insitu_3m_norkyst800_barentswatch_closest_20060101-20220920_seasonal_cycle.nc
forecast_clarify/data/processed/temperature_insitu_3m_norkyst800_barentswatch_closest_20060101-20220920_seasonal_cycle_std.nc
forecast_clarify/data/processed/temperature_insitu_3m_norkyst800_barentswatch_closest_20060101-20220920_trend.nc
forecast_clarify/data/raw/__init__.py
forecast_clarify-0.1.1.dist-info/LICENSE.txt
forecast_clarify-0.1.1.dist-info/METADATA
forecast_clarify-0.1.1.dist-info/WHEEL
forecast_clarify-0.1.1.dist-info/top_level.txt
forecast_clarify-0.1.1.dist-info/RECORD
