Metadata-Version: 2.1
Name: forecast-clarify
Version: 0.1.1
Summary: Local sea surface temperature weekly forecasts based on local statistics (seasonal cycle, week-to-week persistence) and coarse-resolution dynamical forecasts
Home-page: https://github.com/olewu/forecast_clarify
Author: Climate Futures, Clarify
Author-email: owul@norceresearch.no, odd.gunnar@clarify.io
License: MIT
Classifier: Development Status :: 5 - Production/Stable
Classifier: Topic :: Scientific/Engineering
Classifier: Intended Audience :: Science/Research
Classifier: Operating System :: OS Independent
Classifier: Programming Language :: Python
Classifier: Programming Language :: Python :: 3
Classifier: Programming Language :: Python :: 3.6
Classifier: Programming Language :: Python :: 3.7
Classifier: Programming Language :: Python :: 3.8
Classifier: License :: OSI Approved :: MIT License
Requires-Python: >=3.6
License-File: LICENSE.txt
Requires-Dist: numpy
Requires-Dist: pandas
Requires-Dist: requests
Requires-Dist: xarray
Requires-Dist: scikit-learn (==1.1.2)
